sentry_whatsapp
