Metadata-Version: 1.0
Name: sentry-whatsapp
Version: 0.1.3
Summary: A Sentry extension which integrates with Whatsapp™
Home-page: https://github.com/ecarreras/sentry-whatsapp
Author: Eduard Carreras
Author-email: ecarreras@gisce.net
License: BSD
Platform: UNKNOWN
Classifier: Framework :: Django
Classifier: Intended Audience :: Developers
Classifier: Intended Audience :: System Administrators
Classifier: Operating System :: OS Independent
Classifier: Topic :: Software Development
